fastats/__init__.py
fastats/_version.py
fastats/core/__init__.py
fastats/core/decorator.py
fastats/core/single_pass.py
fastats/core/windowed_pass.py
fastats/core/windowed_stateful_pass.py
fastats/core/ast_transforms/__init__.py
fastats/core/ast_transforms/convert_to_jit.py
fastats/core/ast_transforms/copy_func.py
fastats/core/ast_transforms/processor.py
fastats/core/ast_transforms/transformer.py
fastats/kalman/__init__.py
fastats/linear_algebra/__init__.py
fastats/linear_algebra/det.py
fastats/linear_algebra/inv.py
fastats/linear_algebra/lasso.py
fastats/linear_algebra/lu.py
fastats/linear_algebra/matrix_minor.py
fastats/linear_algebra/ols.py
fastats/linear_algebra/pca.py
fastats/linear_algebra/qr.py
fastats/maths/__init__.py
fastats/maths/activations.py
fastats/maths/deriv.py
fastats/maths/erf.py
fastats/maths/erfc.py
fastats/maths/ewma.py
fastats/maths/logistic.py
fastats/maths/norm_cdf.py
fastats/maths/norm_pdf.py
fastats/maths/sum_sq_dev.py
fastats/maths/correlation/__init__.py
fastats/maths/correlation/pearson.py
fastats/maths/correlation/spearman.py
fastats/optimise/__init__.py
fastats/optimise/root_finding/__init__.py
fastats/optimise/root_finding/binary_search.py
fastats/optimise/root_finding/newton_raphson.py
fastats/optimise/solvers/__init__.py
fastats/scaling/__init__.py
fastats/scaling/scaling.py
fastats/utilities/__init__.py
fastats/utilities/arrays.py
fastats-2019.1.dist-info/DESCRIPTION.rst
fastats-2019.1.dist-info/METADATA
fastats-2019.1.dist-info/RECORD
fastats-2019.1.dist-info/WHEEL
fastats-2019.1.dist-info/metadata.json
fastats-2019.1.dist-info/top_level.txt
