Metadata-Version: 2.0
Name: fastats
Version: 2019.1
Summary: A pure Python library for benchmarked, scalable numerics using numba
Home-page: https://github.com/fastats/fastats
Author: UNKNOWN
Author-email: fastats@googlegroups.com
License: UNKNOWN
Keywords: algorithmics ast linear-algebra numba numerics
Platform: UNKNOWN
Classifier: Development Status :: 5 - Production/Stable
Classifier: Intended Audience :: Developers
Classifier: Intended Audience :: Science/Research
Classifier: Topic :: Scientific/Engineering
Classifier: Operating System :: OS Independent
Classifier: License :: OSI Approved :: MIT License
Classifier: Programming Language :: Python :: 3
Classifier: Programming Language :: Python :: 3 :: Only
Classifier: Programming Language :: Python :: 3.5
Classifier: Programming Language :: Python :: 3.6
Classifier: Programming Language :: Python :: 3.7
Requires-Dist: numba (<=0.42,>=0.41)
Requires-Dist: numpy
Requires-Dist: scipy
Provides-Extra: ci_test
Requires-Dist: codecov; extra == 'ci_test'
Requires-Dist: httpie; extra == 'ci_test'
Requires-Dist: hypothesis; extra == 'ci_test'
Requires-Dist: mock; extra == 'ci_test'
Requires-Dist: numba (<=0.42,>=0.41); extra == 'ci_test'
Requires-Dist: numpy; extra == 'ci_test'
Requires-Dist: pandas; extra == 'ci_test'
Requires-Dist: patsy; extra == 'ci_test'
Requires-Dist: pytest; extra == 'ci_test'
Requires-Dist: pytest-cov; extra == 'ci_test'
Requires-Dist: scikit-learn; extra == 'ci_test'
Requires-Dist: scipy; extra == 'ci_test'
Requires-Dist: setuptools; extra == 'ci_test'
Requires-Dist: statsmodels; extra == 'ci_test'
Provides-Extra: dev
Requires-Dist: hypothesis; extra == 'dev'
Requires-Dist: mock; extra == 'dev'
Requires-Dist: numba (<=0.42,>=0.41); extra == 'dev'
Requires-Dist: numpy; extra == 'dev'
Requires-Dist: pandas; extra == 'dev'
Requires-Dist: patsy; extra == 'dev'
Requires-Dist: pytest; extra == 'dev'
Requires-Dist: pytest-cov; extra == 'dev'
Requires-Dist: scikit-learn; extra == 'dev'
Requires-Dist: scipy; extra == 'dev'
Requires-Dist: setuptools; extra == 'dev'
Requires-Dist: sphinx; extra == 'dev'
Requires-Dist: sphinx-rtd-theme; extra == 'dev'
Requires-Dist: statsmodels; extra == 'dev'
Provides-Extra: doc
Requires-Dist: sphinx; extra == 'doc'
Requires-Dist: sphinx-rtd-theme; extra == 'doc'
